{
  "project_info": {
    "project_number": "531215487363",
    "project_id": "drive-exam-1dabf",
    "storage_bucket": "drive-exam-1dabf.appspot.com"
  },
  "client": [
    {
      "client_info": {
        "mobilesdk_app_id": "1:531215487363:android:5f55dfb3344f6a6038a6b6",
        "android_client_info": {
          "package_name": "com.example.thibanglaixe"
        }
      },
      "oauth_client": [
        {
          "client_id": "531215487363-nngesphsgbp4vm9th6dhnlmpgtitch8g.apps.googleusercontent.com",
          "client_type": 3
        }
      ],
      "api_key": [
        {
          "current_key": "AIzaSyBU0-7ZG9V2vwzmykyHJ7f-Rx4cZjfVwsw"
        }
      ],
      "services": {
        "appinvite_service": {
          "other_platform_oauth_client": [
            {
              "client_id": "531215487363-nngesphsgbp4vm9th6dhnlmpgtitch8g.apps.googleusercontent.com",
              "client_type": 3
            }
          ]
        }
      }
    }
  ],
  "configuration_version": "1"
}